README.md
setup.py
BeyondHD_Parser.egg-info/PKG-INFO
BeyondHD_Parser.egg-info/SOURCES.txt
BeyondHD_Parser.egg-info/dependency_links.txt
BeyondHD_Parser.egg-info/requires.txt
BeyondHD_Parser.egg-info/top_level.txt
beyondhd_parser/__init__.py
beyondhd_parser/beyondhd_details.py
beyondhd_parser/beyondhd_search.py
beyondhd_parser/bhdstudio_nfo_parse.py