Metadata-Version: 2.1
Name: BeyondHD-Parser
Version: 1.0.8
Summary: Tool to search/scrape BeyondHD for torrent information
Home-page: https://github.com/jlw4049/BeyondHD-Parser
Author: Jessie Wilson
Author-email: jessielw4049@gmail.com
License: MIT
Keywords: BeyondHD-Parser
Platform: UNKNOWN
Classifier: Development Status :: 5 - Production/Stable
Classifier: Intended Audience :: Developers
Classifier: Operating System :: Microsoft :: Windows
Classifier: Operating System :: MacOS
Classifier: Operating System :: POSIX :: Linux
Classifier: License :: OSI Approved :: MIT License
Classifier: Programming Language :: Python :: 3
